LICENSE
MANIFEST.in
README.md
setup.py
django_theherk_events.egg-info/PKG-INFO
django_theherk_events.egg-info/SOURCES.txt
django_theherk_events.egg-info/dependency_links.txt
django_theherk_events.egg-info/requires.txt
django_theherk_events.egg-info/top_level.txt
events/__init__.py
events/admin.py
events/cms_app.py
events/cms_plugins.py
events/models.py
events/urls.py
events/views.py
events/migrations/0001_initial.py
events/migrations/0002_change_to_all__add_calendarevents.py
events/migrations/__init__.py
events/templates/events/calendar_events.html
events/templates/events/event_detail.html
events/templates/events/index.html
events/templates/events/plugin.html