Metadata-Version: 1.1
Name: django-theherk-events
Version: 1.8.1
Summary: Django CMS plugin to track events on multiple calendars
Home-page: https://github.com/theherk/django-theherk-events
Author: Adam Sherwood
Author-email: theherk@gmail.com
License: see file LICENSE
Download-URL: https://github.com/theherk/django-theherk-events/archive/1.8.1.zip
Platform: UNKNOWN
Classifier: Environment :: Web Environment
Classifier: Framework :: Django
Classifier: Intended Audience :: Developers
Classifier: Operating System :: OS Independent
Classifier: Programming Language :: Python
Classifier: Programming Language :: Python :: 2.6
Classifier: Programming Language :: Python :: 2.7
Classifier: Programming Language :: Python :: 3.3
Classifier: Topic :: Internet :: WWW/HTTP
Classifier: Topic :: Internet :: WWW/HTTP :: Dynamic Content
